drf_haystack/__init__.py
drf_haystack/constants.py
drf_haystack/fields.py
drf_haystack/filters.py
drf_haystack/generics.py
drf_haystack/mixins.py
drf_haystack/query.py
drf_haystack/serializers.py
drf_haystack/utils.py
drf_haystack/viewsets.py
drf_haystack-1.9.1.dist-info/LICENSE.txt
drf_haystack-1.9.1.dist-info/METADATA
drf_haystack-1.9.1.dist-info/WHEEL
drf_haystack-1.9.1.dist-info/top_level.txt
drf_haystack-1.9.1.dist-info/RECORD
